Workbook

Sheet INDEX
B2: EmpID
B3: Name
B4: Title
B5: Business Unit
B6: Grade
B7: Manager
B8: Location
B9: Role/Exp
B10: Function
B11: Compensation
B12: Comp Trend 2022
B13: Comp Trend 2023
B14: Comp Trend 2024
A15: TALENT PROFILE | B15: TR Rating
B16: TR Trend 2022
B17: TR Trend 2023
B18: TR Trend 2024
B19: Ability
B20: Aspiration
B21: Alignment
B22: Perf 24-25 (H1)
B23: Perf 24-25 (H2)
B24: Perf 25-26 (H1)
B25: Risk of Loss
B26: Impact of Loss
B27: Willing to Relocate
A28: LEADERSHIP IMPACT | B28: 360 Assessment
B29: 360 Trend 2022
B30: 360 Trend 2023
B31: 360 Trend 2024
B32: Manager Climate
B33: Climate Trend 2022
B34: Climate Trend 2023
B35: Climate Trend 2024
B36: GPTW Score
B37: GPTW Trend 2022
B38: GPTW Trend 2023
B39: GPTW Trend 2024

Sheet Profile
A1: EmpID | B1: Name | C1: Title | D1: Business Unit | E1: Grade | F1: Manager | G1: Location | H1: Exp in Current Role | I1: Exp in Current Org | J1: Exp in Current Org (Overall Exp) | K1: Current Experience | L1: Previous Experience | M1: Function | N1: Compensation FY 26-27 | O1: Comp Trend FY 25-26 | P1: Comp Trend FY 24-25 | Q1: Total Unvested LTIP Benefit | R1: Last Promotion Date | S1: TR Rating FY 25-26 | T1: TR Trend FY 24-25 | U1: TR Trend FY 23-24 | V1: Ability | W1: Aspiration | X1: Alignment | Y1: Perf 25-26 (H1) | Z1: Perf 24-25 (H2) | AA1: Perf 24-25 (H1) | AB1: Risk of Loss | AC1: Impact of Loss | AD1: Willing to Relocate | AE1: 360 Trend 2025 | AF1: 360 Trend 2023 | AG1: 360 Trend 2024 | AH1: Manager Climate Score FY26-27 | AI1: Manager Climate Score FY24-25 | AJ1: Manager Climate Score FY25-26 | AK1: GPTW Score 2025 | AL1: GPTW Score 2024 | AM1: GPTW Score 2023
A2: 35000745 | B2: Sundeep Kumar | C2: Chief Manager - Projects | D2: Sterlite Electric | E2: M4 | F2: Sharma, Manoj | G2: Project Site - HR | I2: 7 | J2: 23.2 | K2: Chief Business Officer - Overhead & MSI (2021-Present) , Vice President Projects (2019-2021) | L2: Punj Lloyd Limited (2008-2019), Bharat Heavy Electricals Limited (2002-2007), Honda Motorcycle & Scooter India Pvt. Ltd. (2002 – 2002) | M2: Projects Execution | R2: 43719 | S2: 5 | T2: 5 | U2: - | Y2: 80 | Z2: 88 | AA2: 100 | AB2: Medium | AC2: Medium | AD2: No | AE2: - | AH2: 82 | AI2: 90 | AJ2: 89 | AK2: - | AL2: -
A3: 35000172 | B3: Prapin Samanta | C3: Assistant Vice President - Projects | D3: Sterlite Electric | E3: M3 | F3: Tripathi, Avadhesh | G3: Project Site - WB | I3: 7 | J3: 23.2 | K3: CFO- SEL (2026- Present) | L3: Tenneco Clean Air India Limited (2024-2026), Azure Power India Pvt Ltd (2023-2024), Sterlite Power Transmission Ltd ( 2019-20223) | M3: Projects Execution | S3: 5 | T3: 5 | U3: 5 | Y3: 105 | Z3: - | AA3: - | AB3: Medium | AC3: Medium | AD3: Yes | AE3: - | AH3: 78 | AI3: 67 | AJ3: 91 | AK3: - | AL3: -
A4: 35000985 | B4: Aashif Alam | C4: Chief Manager- Projects (Wind) | D4: Serentica | E4: M4 | F4: Chakraborty, Amit Kumar | G4: Project Site - MH | I4: 7 | J4: 23.2 | K4: Head- Strategy & M&A (2026-Present), VP - Strategy & Finance, MD Office (2024-2026) | L4: Suminter India Organic (2023-2024), Bajaj Electricals Ltd (2019-2023), Voltas Ltd (2016-2019) | M4: Projects Execution | S4: 5 | T4: 5 | U4: - | Y4: 120 | Z4: 110 | AA4: 100 | AB4: Medium | AC4: Medium | AD4: Yes | AE4: - | AH4: 66 | AI4: 88 | AJ4: 82 | AK4: 84 | AL4: -
A5: 35001312 | B5: Prashant Sinha | C5: CEO - Resonia | D5: Resonia | E5: M1A | F5: Agarwal, Pratik | G5: Mumbai - BKC | I5: 1.8 | J5: 12 | K5: Head - Manufacturing Operations (2026-Present), Vice President - Manufacturing Operations (2024-2026) | L5: Indoasian Legrand Group (1999-2024) | M5: Projects Execution | R5: 43565 | S5: 8 | T5: 8 | U5: - | Y5: 90 | Z5: 95 | AA5: - | AB5: Low | AC5: High | AD5: No | AE5: 4.27 | AH5: 89 | AI5: 89 | AJ5: 90 | AK5: 89 | AL5: -
A6: 35001546 | B6: Harish kumar | C6: Chief Manager- Projects (Wind) | D6: Serentica | E6: M4A | F6: J, Balakrishnan | G6: Project Site - KA | I6: 3.8 | J6: 14 | K6: Head- Strategy & M&A (2026-Present), VP - Strategy & Finance, MD Office (2024-2026) | L6: Suminter India Organic (2023-2024), Bajaj Electricals Ltd (2019-2023), Voltas Ltd (2016-2019) | M6: Projects Execution | R6: 44119 | S6: 5 | T6: - | U6: - | Y6: 95 | Z6: 98 | AA6: 100 | AB6: Medium | AC6: Medium | AD6: Yes | AE6: - | AH6: - | AI6: - | AJ6: - | AK6: - | AL6: -
A7: 24900238 | B7: Prashant Saha | C7: Chief Manager - Production | D7: Sterlite Electric | E7: M4A | F7: Chowdhury, Ratul | G7: Rakholi Plant - DNH | I7: 0 | J7: 19.7 | K7: CFO- SEL (2026- Present) | L7: Tenneco Clean Air India Limited (2024-2026), Azure Power India Pvt Ltd (2023-2024), Sterlite Power Transmission Ltd ( 2019-20223) | M7: Manufacturing | S7: 5 | T7: 5 | U7: 5 | Y7: 80 | Z7: 88 | AA7: 100 | AB7: Medium | AC7: Medium | AD7: No | AE7: - | AH7: 82 | AI7: 90 | AJ7: 89 | AK7: - | AL7: -
A8: 35001906 | B8: Suraj Parkash | C8: Chief Manager - Production | D8: Sterlite Electric | E8: M4 | F8: Kumar, Santosh | G8: Jharsuguda Plant - OR | I8: 2.2 | J8: 29.5 | K8: Head - Manufacturing Operations (2026-Present), Vice President - Manufacturing Operations (2024-2026) | L8: Indoasian Legrand Group (1999-2024) | M8: Manufacturing | S8: 5 | T8: - | U8: - | Y8: 105 | Z8: 102 | AA8: 110 | AB8: High | AC8: High | AD8: No | AE8: - | AH8: 78 | AI8: 67 | AJ8: 91 | AK8: - | AL8: -
A9: 35001762 | B9: Ankit Agrawal | C9: Chief Manager - S&OP | D9: Sterlite Electric | E9: M4 | F9: Mattoo, Surinder | G9: Gurugram Office | I9: 1.8 | J9: 12 | K9: Head- Strategy & M&A (2026-Present), VP - Strategy & Finance, MD Office (2024-2026) | L9: Suminter India Organic (2023-2024), Bajaj Electricals Ltd (2019-2023), Voltas Ltd (2016-2019) | M9: Sales | S9: 5 | T9: - | U9: - | Y9: 120 | Z9: 110 | AA9: 100 | AB9: Low | AC9: Low | AD9: Yes | AE9: - | AH9: 66 | AI9: 88 | AJ9: 82 | AK9: - | AL9: -
A10: 24903846 | B10: Amey Sukhthanker | C10: Vice President- Sales and Alliance | D10: Sterlite Electric | E10: M2 | F10: Deshraj, Surya Rajshekhar | G10: Mumbai - Vikhroli | I10: 3.8 | J10: 14 | K10: Chief Business Officer - Overhead & MSI (2021-Present) , Vice President Projects (2019-2021) | L10: Punj Lloyd Limited (2008-2019), Bharat Heavy Electricals Limited (2002-2007), Honda Motorcycle & Scooter India Pvt. Ltd. (2002 – 2002) | M10: Convergence | S10: 6 | T10: 6 | U10: 5 | Y10: 90 | Z10: 95 | AA10: 99 | AB10: High | AC10: High | AD10: No | AE10: - | AH10: 89 | AI10: 89 | AJ10: 90 | AK10: - | AL10: -
A11: 35001657 | B11: Deepak Jaiswal | C11: Chief Manager - Billing and Collections | D11: Sterlite Electric | E11: M4 | F11: Sukhthanker, Amey | G11: Gurugram Office | I11: 7 | J11: 23.2 | K11: CFO- SEL (2026- Present) | L11: Tenneco Clean Air India Limited (2024-2026), Azure Power India Pvt Ltd (2023-2024), Sterlite Power Transmission Ltd ( 2019-20223) | M11: Convergence | S11: 5 | T11: - | U11: - | Y11: 95 | Z11: 98 | AA11: 100 | AB11: Low | AC11: Medium | AD11: Yes | AE11: - | AH11: - | AI11: - | AJ11: - | AK11: - | AL11: -
A12: 24900651 | B12: Nishant Tyagi | C12: Chief Manager - Manufacturing | D12: Sterlite Electric | E12: M4A | F12: Bhati, Himanshu | G12: Haridwar Plant - UKH | I12: 0 | J12: 19.7 | K12: Head - Manufacturing Operations (2026-Present), Vice President - Manufacturing Operations (2024-2026) | L12: Indoasian Legrand Group (1999-2024) | M12: Manufacturing | S12: 6 | T12: 6 | U12: 5 | Y12: 80 | Z12: 88 | AA12: 100 | AB12: High | AC12: High | AD12: Yes | AE12: - | AH12: - | AI12: - | AJ12: - | AK12: - | AL12: -
A13: 24901511 | B13: Hemsingh Hansawat | C13: Chief Manager - Customer Support Organization | D13: Sterlite Electric | E13: M4 | F13: Kapoor, Lokesh | G13: Haridwar Plant - UKH | I13: 2.2 | J13: 29.5 | K13: Head- Strategy & M&A (2026-Present), VP - Strategy & Finance, MD Office (2024-2026) | L13: Suminter India Organic (2023-2024), Bajaj Electricals Ltd (2019-2023), Voltas Ltd (2016-2019) | M13: Sales | S13: 3 | T13: 5 | U13: - | Y13: 105 | Z13: 102 | AA13: 110 | AB13: Low | AC13: Medium | AD13: Yes | AE13: - | AH13: - | AI13: - | AJ13: - | AK13: - | AL13: -
A14: 24901832 | B14: Kishore Amitraj | C14: Assistant Vice President - Claims & Contracts | D14: Sterlite Electric | E14: M3 | F14: Bhardwaj, Ankit | G14: Gurugram Office | I14: 1.8 | J14: 12 | K14: Chief Business Officer - Overhead & MSI (2021-Present) , Vice President Projects (2019-2021) | L14: Punj Lloyd Limited (2008-2019), Bharat Heavy Electricals Limited (2002-2007), Honda Motorcycle & Scooter India Pvt. Ltd. (2002 – 2002) | M14: Projects Execution | S14: 5 | T14: 5 | U14: 5 | Y14: 120 | Z14: - | AA14: - | AB14: Medium | AC14: High | AD14: No | AE14: - | AH14: - | AI14: - | AJ14: - | AK14: - | AL14: -
A15: 24903159 | B15: Kamal Khanna | C15: Assistant Vice President - Product Development | D15: Sterlite Electric | E15: M3 | F15: Mattoo, Surinder | G15: Gurugram Office | I15: 3.8 | J15: 14 | K15: CFO- SEL (2026- Present) | L15: Tenneco Clean Air India Limited (2024-2026), Azure Power India Pvt Ltd (2023-2024), Sterlite Power Transmission Ltd ( 2019-20223) | M15: Plant NPD | S15: 6 | T15: 5 | U15: 6 | Y15: - | Z15: - | AA15: - | AB15: Medium | AC15: High | AD15: Yes | AE15: - | AH15: 78 | AI15: 79 | AJ15: 80 | AK15: - | AL15: -
A16: 35001576 | B16: Divya Vyas | C16: Chief Manager - Cable Exports | D16: Sterlite Electric | E16: M4 | F16: Gupta, Vibhor | G16: Gurugram Office | I16: 7 | J16: 23.2 | K16: Head - Manufacturing Operations (2026-Present), Vice President - Manufacturing Operations (2024-2026) | L16: Indoasian Legrand Group (1999-2024) | M16: Sales | S16: 5 | T16: - | U16: - | Y16: 95 | Z16: - | AA16: 100 | AB16: Medium | AC16: High | AD16: Yes | AE16: - | AH16: 89 | AI16: 90 | AJ16: 88 | AK16: - | AL16: -
A17: 35001891 | B17: Abdul Samad jailaani | C17: Chief Manager - Manufacturing | D17: Sterlite Electric | E17: M4A | F17: Jaiswal, Rahul | G17: Vadodara Plant – GJ | I17: 0 | J17: 19.7 | K17: Head- Strategy & M&A (2026-Present), VP - Strategy & Finance, MD Office (2024-2026) | L17: Suminter India Organic (2023-2024), Bajaj Electricals Ltd (2019-2023), Voltas Ltd (2016-2019) | M17: Manufacturing | S17: 5 | T17: - | U17: - | Y17: 80 | Z17: 88 | AA17: 100 | AB17: Low | AC17: High | AD17: Yes | AE17: - | AH17: 82 | AI17: 90 | AJ17: 89 | AK17: - | AL17: -
A18: 24903188 | B18: Arpit Shrivastava | C18: Chief Manager - Service Delivery | D18: Sterlite Electric | E18: M4 | F18: Dangat, Nilesh | G18: Mumbai - Vikhroli | I18: 2.2 | J18: 29.5 | K18: Chief Business Officer - Overhead & MSI (2021-Present) , Vice President Projects (2019-2021) | L18: Punj Lloyd Limited (2008-2019), Bharat Heavy Electricals Limited (2002-2007), Honda Motorcycle & Scooter India Pvt. Ltd. (2002 – 2002) | M18: Convergence | R18: 43719 | S18: 6 | T18: 5 | U18: - | Y18: 105 | Z18: 102 | AA18: 110 | AB18: Medium | AC18: High | AD18: No | AE18: - | AH18: 78 | AI18: 67 | AJ18: 91 | AK18: - | AL18: -
A19: 35001670 | B19: Sayantani Mitra | C19: Assistant Vice President - Business Development & Market Intelligence | D19: Sterlite Electric | E19: M3 | F19: Bhardwaj, Ankit | G19: Mumbai Office | I19: 1.8 | J19: 12 | K19: CFO- SEL (2026- Present) | L19: Tenneco Clean Air India Limited (2024-2026), Azure Power India Pvt Ltd (2023-2024), Sterlite Power Transmission Ltd ( 2019-20223) | M19: Marketing | S19: 5 | T19: - | U19: - | Y19: 120 | Z19: 110 | AA19: 100 | AB19: High | AC19: High | AD19: Yes | AE19: - | AH19: 66 | AI19: 88 | AJ19: 82 | AK19: - | AL19: -
A20: 24900040 | B20: Shijo Thomas | C20: Assistant Vice President - S&OP | D20: Sterlite Electric | E20: M3 | F20: Mattoo, Surinder | G20: Gurugram Office | I20: 3.8 | J20: 14 | K20: Head - Manufacturing Operations (2026-Present), Vice President - Manufacturing Operations (2024-2026) | L20: Indoasian Legrand Group (1999-2024) | M20: Manufacturing | S20: 8 | T20: 5 | U20: 5 | Y20: 80 | Z20: 88 | AA20: 100 | AB20: Medium | AC20: High | AD20: Yes | AE20: - | AH20: 89 | AI20: 89 | AJ20: 90 | AK20: - | AL20: -
A21: 35000091 | B21: Priyank Kumar Shrivastava | C21: Chief Manager - Service Delivery | D21: Sterlite Electric | E21: M4 | F21: Dangat, Nilesh | G21: Project Site - RJ | I21: 7 | J21: 23.2 | K21: Head- Strategy & M&A (2026-Present), VP - Strategy & Finance, MD Office (2024-2026) | L21: Suminter India Organic (2023-2024), Bajaj Electricals Ltd (2019-2023), Voltas Ltd (2016-2019) | M21: Convergence | S21: 5 | T21: 5 | U21: 5 | Y21: 105 | Z21: 102 | AA21: 110 | AB21: Low | AC21: Medium | AD21: Yes | AE21: - | AH21: - | AI21: - | AJ21: - | AK21: - | AL21: -
A22: 35001162 | B22: Nitin Malhotra | C22: Chief Manager - Sales & Business Development (Power Cables) | D22: Sterlite Electric | E22: M4A | F22: Kapoor, Lokesh | G22: Gurugram Office | I22: 0 | J22: 19.7 | K22: Chief Business Officer - Overhead & MSI (2021-Present) , Vice President Projects (2019-2021) | L22: Punj Lloyd Limited (2008-2019), Bharat Heavy Electricals Limited (2002-2007), Honda Motorcycle & Scooter India Pvt. Ltd. (2002 – 2002) | M22: Sales | S22: 5 | T22: 4 | U22: - | Y22: 120 | Z22: 110 | AA22: 100 | AB22: Medium | AC22: Medium | AD22: No | AE22: - | AH22: 82 | AI22: 90 | AJ22: 89 | AK22: - | AL22: -
A23: 35001066 | B23: Sunil Kumar Choubey | C23: Assistant Vice President - Projects Execution | D23: Sterlite Electric | E23: M3 | F23: Mattoo, Surinder | G23: Vadodara Plant – GJ | I23: 2.2 | J23: 29.5 | K23: CFO- SEL (2026- Present) | L23: Tenneco Clean Air India Limited (2024-2026), Azure Power India Pvt Ltd (2023-2024), Sterlite Power Transmission Ltd ( 2019-20223) | M23: Projects Execution | S23: 8 | T23: 8 | U23: 5 | Y23: 90 | Z23: 95 | AA23: 99 | AB23: High | AC23: High | AD23: Yes | AE23: - | AH23: 78 | AI23: 67 | AJ23: 91 | AK23: 94 | AL23: -
A24: 35001628 | B24: Yogish Vijay Sarang | C24: Sales Director | D24: Sterlite Electric | E24: M2 | F24: Bhardwaj, Ankit | G24: Mumbai Office | I24: 1.8 | J24: 12 | K24: Head - Manufacturing Operations (2026-Present), Vice President - Manufacturing Operations (2024-2026) | L24: Indoasian Legrand Group (1999-2024) | M24: Sales | R24: 43719 | S24: 5 | T24: 5 | U24: - | Y24: 95 | Z24: 98 | AA24: 100 | AB24: High | AC24: High | AD24: Yes | AE24: 3.67 | AH24: 66 | AI24: 88 | AJ24: 82 | AK24: - | AL24: -
A25: 35001667 | B25: Meenakshi Thusu | C25: Chief Manager - Production Planning & Control | D25: Sterlite Electric | E25: M4 | F25: Bhati, Himanshu | G25: Haridwar Plant - UKH | I25: 3.8 | J25: 14 | K25: Head- Strategy & M&A (2026-Present), VP - Strategy & Finance, MD Office (2024-2026) | L25: Suminter India Organic (2023-2024), Bajaj Electricals Ltd (2019-2023), Voltas Ltd (2016-2019) | M25: Manufacturing | S25: 8 | T25: - | U25: - | Y25: 80 | Z25: 88 | AA25: 100 | AB25: Medium | AC25: High | AD25: Yes | AE25: - | AH25: 89 | AI25: 89 | AJ25: 90 | AK25: - | AL25: -
A26: 35001218 | B26: Kiran Anant Patil | C26: Chief Manager - Operations | D26: Sterlite Electric | E26: M4 | F26: Choubey, Sunil Kumar | G26: Vadodara Plant – GJ | I26: 7 | J26: 23.2 | K26: Chief Business Officer - Overhead & MSI (2021-Present) , Vice President Projects (2019-2021) | L26: Punj Lloyd Limited (2008-2019), Bharat Heavy Electricals Limited (2002-2007), Honda Motorcycle & Scooter India Pvt. Ltd. (2002 – 2002) | M26: Manufacturing | S26: 5 | T26: 5 | U26: - | Y26: 105 | Z26: 102 | AA26: 110 | AB26: Medium | AC26: Medium | AD26: Yes | AE26: - | AH26: - | AI26: - | AJ26: - | AK26: - | AL26: -
A27: 35001383 | B27: Sisir Kumar Parida | C27: Chief Manager - Projects | D27: Sterlite Electric | E27: M4 | F27: Sharma, Satyendra Kumar | G27: Project Site - OR | I27: 0 | J27: 19.7 | K27: CFO- SEL (2026- Present) | L27: Tenneco Clean Air India Limited (2024-2026), Azure Power India Pvt Ltd (2023-2024), Sterlite Power Transmission Ltd ( 2019-20223) | M27: Projects Execution | R27: 43565 | S27: 1 | T27: 2 | U27: - | Y27: 120 | Z27: 110 | AA27: 100 | AB27: High | AC27: High | AD27: Yes | AE27: - | AH27: - | AI27: - | AJ27: - | AK27: - | AL27: -
A28: 24902509 | B28: Pawan Jain | C28: Chief Manager - Quality | D28: Sterlite Electric | E28: M4A | F28: Gulati, Rajesh Kumar | G28: Haridwar Plant - UKH | I28: 2.2 | J28: 29.5 | K28: Head - Manufacturing Operations (2026-Present), Vice President - Manufacturing Operations (2024-2026) | L28: Indoasian Legrand Group (1999-2024) | M28: QHSE | R28: 44119 | S28: 5 | T28: 5 | U28: 5 | Y28: 90 | Z28: 95 | AA28: 99 | AB28: Medium | AC28: Medium | AD28: Yes | AE28: - | AH28: - | AI28: - | AJ28: - | AK28: - | AL28: -
A29: 35000704 | B29: Manas Kumar | C29: Chief Manager - Quality, Health, Environment & Safety | D29: Sterlite Electric | E29: M4A | F29: Singh, Akhilesh | G29: Gurugram Office | I29: 1.8 | J29: 12 | K29: Head- Strategy & M&A (2026-Present), VP - Strategy & Finance, MD Office (2024-2026) | L29: Suminter India Organic (2023-2024), Bajaj Electricals Ltd (2019-2023), Voltas Ltd (2016-2019) | M29: QHSE | S29: 5 | T29: 5 | U29: 5 | Y29: 95 | Z29: 98 | AA29: 100 | AB29: Medium | AC29: High | AD29: No | AE29: - | AH29: 78 | AI29: 79 | AJ29: 80 | AK29: - | AL29: -
A30: 35001931 | B30: Balaji Rao Thorhath | C30: Chief Manager - Sales & Business Development (Power Cables) | D30: Sterlite Electric | E30: M4 | F30: Kapoor, Lokesh | G30: Project Site - KA | I30: 3.8 | J30: 14 | K30: Chief Business Officer - Overhead & MSI (2021-Present) , Vice President Projects (2019-2021) | L30: Punj Lloyd Limited (2008-2019), Bharat Heavy Electricals Limited (2002-2007), Honda Motorcycle & Scooter India Pvt. Ltd. (2002 – 2002) | M30: Sales | S30: 5 | T30: - | U30: - | Y30: 80 | Z30: 88 | AA30: 100 | AB30: Low | AC30: Medium | AD30: No | AE30: - | AH30: 89 | AI30: 90 | AJ30: 88 | AK30: - | AL30: -
A31: 35000422 | B31: Ankit Bhardwaj | C31: Chief Business Officer - Overhead & MSI | D31: Sterlite Electric | E31: M1 | F31: Trefois, Frederic | G31: Gurugram Office | I31: 7 | J31: 23.2 | K31: CFO- SEL (2026- Present) | L31: Tenneco Clean Air India Limited (2024-2026), Azure Power India Pvt Ltd (2023-2024), Sterlite Power Transmission Ltd ( 2019-20223) | M31: Projects Execution | S31: 5 | T31: 7 | U31: 8 | Y31: 105 | Z31: 102 | AA31: 110 | AB31: Medium | AC31: High | AD31: No | AE31: - | AH31: 82 | AI31: 90 | AJ31: 89 | AK31: - | AL31: 83
A32: 35001199 | B32: Rabi Prasad | C32: Chief Manager - Health, Environment & Safety | D32: Sterlite Electric | E32: M4 | F32: GOUDA, VISHNU NATH | G32: Rakholi Plant - DNH | I32: 0 | J32: 19.7 | K32: Head - Manufacturing Operations (2026-Present), Vice President - Manufacturing Operations (2024-2026) | L32: Indoasian Legrand Group (1999-2024) | M32: QHSE | S32: 2 | T32: 4 | U32: - | Y32: 120 | Z32: - | AA32: - | AB32: High | AC32: High | AD32: Yes | AE32: - | AH32: 78 | AI32: 67 | AJ32: 91 | AK32: - | AL32: -
A33: 24903254 | B33: Rajesh Kumar Gulati | C33: Assistant Vice President - Quality | D33: Sterlite Electric | E33: M3A | F33: Biswas, Dhritiman | G33: Haridwar Plant - UKH | I33: 2.2 | J33: 29.5 | K33: Head- Strategy & M&A (2026-Present), VP - Strategy & Finance, MD Office (2024-2026) | L33: Suminter India Organic (2023-2024), Bajaj Electricals Ltd (2019-2023), Voltas Ltd (2016-2019) | M33: QHSE | S33: 5 | T33: 5 | U33: 5 | Y33: - | Z33: - | AA33: - | AB33: High | AC33: High | AD33: Yes | AE33: - | AH33: 66 | AI33: 88 | AJ33: 82 | AK33: - | AL33: -
A34: 24903716 | B34: Prasad S | C34: Chief Manager - Plant NPD | D34: Sterlite Electric | E34: M4A | F34: Mattoo, Surinder | G34: Piparia Plant - DNH | I34: 1.8 | J34: 12 | K34: Chief Business Officer - Overhead & MSI (2021-Present) , Vice President Projects (2019-2021) | L34: Punj Lloyd Limited (2008-2019), Bharat Heavy Electricals Limited (2002-2007), Honda Motorcycle & Scooter India Pvt. Ltd. (2002 – 2002) | M34: Plant NPD | S34: 8 | T34: 8 | U34: 8 | Y34: 95 | Z34: - | AA34: 100 | AB34: High | AC34: High | AD34: Yes | AE34: - | AH34: 89 | AI34: 89 | AJ34: 90 | AK34: - | AL34: -
A35: 35000240 | B35: Mohd Wasiqur Rahman | C35: Chief Manager - Service Delivery | D35: Sterlite Electric | E35: M4 | F35: Dangat, Nilesh | G35: Gurugram Office | I35: 3.8 | J35: 14 | K35: CFO- SEL (2026- Present) | L35: Tenneco Clean Air India Limited (2024-2026), Azure Power India Pvt Ltd (2023-2024), Sterlite Power Transmission Ltd ( 2019-20223) | M35: Convergence | S35: 6 | T35: - | U35: - | Y35: 80 | Z35: 88 | AA35: 100 | AB35: Low | AC35: High | AD35: Yes | AE35: - | AH35: - | AI35: - | AJ35: - | AK35: - | AL35: -
A36: 24900448 | B36: Jignesh U Panchal | C36: Chief Manager - Maintenance | D36: Sterlite Electric | E36: M4A | F36: Chowdhury, Ratul | G36: Piparia Plant - DNH | I36: 7 | J36: 23.2 | K36: Head - Manufacturing Operations (2026-Present), Vice President - Manufacturing Operations (2024-2026) | L36: Indoasian Legrand Group (1999-2024) | M36: Manufacturing | S36: 5 | T36: 5 | U36: 5 | Y36: 105 | Z36: 102 | AA36: 110 | AB36: Medium | AC36: High | AD36: No | AE36: - | AH36: 82 | AI36: 90 | AJ36: 89 | AK36: - | AL36: -
A37: 35001325 | B37: VISHNU NATH GOUDA | C37: Assistant Vice President- Products Safety | D37: Sterlite Electric | E37: M3 | F37: Mattoo, Surinder | G37: Rakholi Plant - DNH | I37: 0 | J37: 19.7 | K37: Head- Strategy & M&A (2026-Present), VP - Strategy & Finance, MD Office (2024-2026) | L37: Suminter India Organic (2023-2024), Bajaj Electricals Ltd (2019-2023), Voltas Ltd (2016-2019) | M37: QHSE | S37: 2 | T37: 4 | U37: - | Y37: 120 | Z37: 110 | AA37: 100 | AB37: Medium | AC37: Low | AD37: Yes | AE37: - | AH37: 78 | AI37: 67 | AJ37: 91 | AK37: - | AL37: -
A38: 35001160 | B38: Vibhor Gupta | C38: Sales Director | D38: Sterlite Electric | E38: M3A | F38: Biswas, Dhritiman | G38: Gurugram Office | I38: 2.2 | J38: 29.5 | K38: Chief Business Officer - Overhead & MSI (2021-Present) , Vice President Projects (2019-2021) | L38: Punj Lloyd Limited (2008-2019), Bharat Heavy Electricals Limited (2002-2007), Honda Motorcycle & Scooter India Pvt. Ltd. (2002 – 2002) | M38: Sales | S38: 5 | T38: 8 | U38: - | Y38: 80 | Z38: 88 | AA38: 100 | AB38: High | AC38: High | AD38: Yes | AE38: - | AH38: 66 | AI38: 88 | AJ38: 82 | AK38: - | AL38: -
A39: 24902186 | B39: Sankarganesh Kesavan | C39: Chief Manager - Projects | D39: Sterlite Electric | E39: M4 | F39: Bhardwaj, Ankit | G39: Project Site - TN | I39: 1.8 | J39: 12 | K39: CFO- SEL (2026- Present) | L39: Tenneco Clean Air India Limited (2024-2026), Azure Power India Pvt Ltd (2023-2024), Sterlite Power Transmission Ltd ( 2019-20223) | M39: Projects Execution | S39: 5 | T39: 3 | U39: 2 | Y39: 105 | Z39: - | AA39: - | AB39: Medium | AC39: Medium | AD39: Yes | AE39: - | AH39: 89 | AI39: 89 | AJ39: 90 | AK39: - | AL39: -
A40: 35000935 | B40: Chaitan Goyal | C40: Head Strategic Sourcing | D40: Sterlite Electric | E40: M3A | F40: Trefois, Frederic | G40: Gurugram Office | I40: 3.8 | J40: 14 | K40: Head - Manufacturing Operations (2026-Present), Vice President - Manufacturing Operations (2024-2026) | L40: Indoasian Legrand Group (1999-2024) | M40: Supply Chain Management | S40: 6 | T40: 9 | U40: 8 | Y40: 120 | Z40: 110 | AA40: 100 | AB40: High | AC40: High | AD40: Yes | AE40: - | AH40: - | AI40: - | AJ40: - | AK40: - | AL40: -
A41: 24900985 | B41: Abhishek Singh | C41: Chief Manager - Supply Chain, Logistics | D41: Sterlite Electric | E41: M4 | F41: Chhetry, Debendra | G41: Piparia Plant - DNH | I41: 7 | J41: 23.2 | K41: Head- Strategy & M&A (2026-Present), VP - Strategy & Finance, MD Office (2024-2026) | L41: Suminter India Organic (2023-2024), Bajaj Electricals Ltd (2019-2023), Voltas Ltd (2016-2019) | M41: Supply Chain Management | S41: 5 | T41: 5 | U41: 5 | Y41: 90 | Z41: 95 | AA41: - | AB41: Medium | AC41: High | AD41: Yes | AE41: - | AH41: - | AI41: - | AJ41: - | AK41: - | AL41: -
A42: 24901347 | B42: Jaswant Singh | C42: Chief Manager - Production | D42: Sterlite Electric | E42: M4 | F42: Bhati, Himanshu | G42: Haridwar Plant - UKH | I42: 0 | J42: 19.7 | K42: Chief Business Officer - Overhead & MSI (2021-Present) , Vice President Projects (2019-2021) | L42: Punj Lloyd Limited (2008-2019), Bharat Heavy Electricals Limited (2002-2007), Honda Motorcycle & Scooter India Pvt. Ltd. (2002 – 2002) | M42: Manufacturing | S42: 5 | T42: 5 | U42: - | Y42: 95 | Z42: 98 | AA42: 100 | AB42: High | AC42: High | AD42: Yes | AE42: - | AH42: - | AI42: - | AJ42: - | AK42: - | AL42: -
A43: 35001098 | B43: Akhilesh Singh | C43: Vice President - QHSE | D43: Sterlite Electric | E43: M2 | F43: Bhardwaj, Ankit | G43: Gurugram Office | I43: 2.2 | J43: 29.5 | K43: CFO- SEL (2026- Present) | L43: Tenneco Clean Air India Limited (2024-2026), Azure Power India Pvt Ltd (2023-2024), Sterlite Power Transmission Ltd ( 2019-20223) | M43: QHSE | S43: 6 | T43: 8 | U43: - | Y43: 80 | Z43: 88 | AA43: 100 | AB43: High | AC43: High | AD43: Yes | AE43: 4.55 | AH43: 82 | AI43: 90 | AJ43: 89 | AK43: - | AL43: -
A44: 35001395 | B44: Shreya Nandgaonkar | C44: Chief Manager - EXIM | D44: Sterlite Electric | E44: M4 | F44: Goyal, Chaitan | G44: Mumbai - Vikhroli | I44: 1.8 | J44: 12 | K44: Head - Manufacturing Operations (2026-Present), Vice President - Manufacturing Operations (2024-2026) | L44: Indoasian Legrand Group (1999-2024) | M44: Supply Chain Management | S44: 6 | T44: 5 | U44: - | Y44: 105 | Z44: 102 | AA44: 110 | AB44: Medium | AC44: High | AD44: Yes | AE44: - | AH44: 78 | AI44: 67 | AJ44: 91 | AK44: - | AL44: -
A45: 35001089 | B45: Nilesh Dangat | C45: Assistant Vice President - Service Delivery | D45: Sterlite Electric | E45: M3 | F45: Deshraj, Surya Rajshekhar | G45: Mumbai - Vikhroli | I45: 3.8 | J45: 14 | K45: Head- Strategy & M&A (2026-Present), VP - Strategy & Finance, MD Office (2024-2026) | L45: Suminter India Organic (2023-2024), Bajaj Electricals Ltd (2019-2023), Voltas Ltd (2016-2019) | M45: Convergence | S45: 6 | T45: 5 | U45: 5 | Y45: 120 | Z45: 110 | AA45: 100 | AB45: High | AC45: High | AD45: Yes | AE45: - | AH45: 66 | AI45: 88 | AJ45: 82 | AK45: 98 | AL45: 99
A46: 35000812 | B46: Daya Shankar Shukla | C46: Chief Manager - Bidding & Tendering | D46: Sterlite Electric | E46: M4A | F46: Bhardwaj, Ankit | G46: Gurugram Office | I46: 7 | J46: 23.2 | K46: Chief Business Officer - Overhead & MSI (2021-Present) , Vice President Projects (2019-2021) | L46: Punj Lloyd Limited (2008-2019), Bharat Heavy Electricals Limited (2002-2007), Honda Motorcycle & Scooter India Pvt. Ltd. (2002 – 2002) | M46: Sales | S46: 5 | T46: 5 | U46: 5 | Y46: 90 | Z46: 95 | AA46: 99 | AB46: Medium | AC46: Medium | AD46: Yes | AE46: - | AH46: 89 | AI46: 89 | AJ46: 90 | AK46: - | AL46: -
A47: 35000207 | B47: Vipin Kumar Gaur | C47: Assistant Vice President - SCM | D47: Sterlite Electric | E47: M3A | F47: Bhardwaj, Ankit | G47: Gurugram Office | I47: 0 | J47: 19.7 | K47: CFO- SEL (2026- Present) | L47: Tenneco Clean Air India Limited (2024-2026), Azure Power India Pvt Ltd (2023-2024), Sterlite Power Transmission Ltd ( 2019-20223) | M47: Supply Chain Management | S47: 6 | T47: 5 | U47: 5 | Y47: 95 | Z47: 98 | AA47: 100 | AB47: Medium | AC47: Medium | AD47: Yes | AE47: - | AH47: - | AI47: - | AJ47: - | AK47: - | AL47: -
A48: 35002034 | B48: Somen Das | C48: Chief Manager - Market Analyst | D48: Sterlite Electric | E48: M4A | F48: Biswas, Dhritiman | G48: Gurugram Office | I48: 2.2 | J48: 29.5 | K48: Head - Manufacturing Operations (2026-Present), Vice President - Manufacturing Operations (2024-2026) | L48: Indoasian Legrand Group (1999-2024) | M48: Growth | S48: 8 | T48: - | U48: - | Y48: 80 | Z48: 88 | AA48: 100 | AB48: Medium | AC48: High | AD48: Yes | AE48: - | AH48: 82 | AI48: 90 | AJ48: 89 | AK48: - | AL48: -
A49: 35000894 | B49: Zartab Alam | C49: Lead SS Civil Engineering | D49: Resonia | E49: M4A | F49: Kumar, Harish | G49: Gurugram Office | I49: 1.8 | J49: 12 | K49: Head- Strategy & M&A (2026-Present), VP - Strategy & Finance, MD Office (2024-2026) | L49: Suminter India Organic (2023-2024), Bajaj Electricals Ltd (2019-2023), Voltas Ltd (2016-2019) | M49: Design & Engineering | S49: 8 | T49: 5 | U49: 5 | Y49: 105 | Z49: 102 | AA49: 110 | AB49: Low | AC49: High | AD49: No | AE49: - | AH49: 78 | AI49: 67 | AJ49: 91 | AK49: - | AL49: -
A50: 35000565 | B50: Anuj Krishnavadan Gandhi | C50: Chief Information Officer | D50: Corporate | E50: M2A | F50: Mathur, Sumil | G50: Mumbai - BKC | I50: 3.8 | J50: 14 | K50: Chief Business Officer - Overhead & MSI (2021-Present) , Vice President Projects (2019-2021) | L50: Punj Lloyd Limited (2008-2019), Bharat Heavy Electricals Limited (2002-2007), Honda Motorcycle & Scooter India Pvt. Ltd. (2002 – 2002) | M50: Information Technology | S50: 6 | T50: 5 | U50: 8 | Y50: 120 | Z50: - | AA50: - | AB50: Medium | AC50: High | AD50: No | AE50: 4.3575 | AH50: 66 | AI50: 88 | AJ50: 82 | AK50: 89 | AL50: 71
A51: 35001244 | B51: Anju Yadav | C51: Chief Manager - SAP MM | D51: Corporate | E51: M4 | F51: Rao, Neeraj | G51: Gurugram Office | I51: 7 | J51: 23.2 | K51: CFO- SEL (2026- Present) | L51: Tenneco Clean Air India Limited (2024-2026), Azure Power India Pvt Ltd (2023-2024), Sterlite Power Transmission Ltd ( 2019-20223) | M51: Information Technology | S51: 2 | T51: 5 | U51: - | Y51: - | Z51: - | AA51: - | AB51: Low | AC51: Medium | AD51: No | AE51: - | AH51: 89 | AI51: 89 | AJ51: 90 | AK51: - | AL51: -
A52: 35001011 | B52: Jagveer Gehlaut | C52: Chief Manager - Projects Execution | D52: Resonia | E52: M4A | F52: Verma, Praveen Kumar | G52: Project Site - RJ | I52: 0 | J52: 19.7 | K52: Head - Manufacturing Operations (2026-Present), Vice President - Manufacturing Operations (2024-2026) | L52: Indoasian Legrand Group (1999-2024) | M52: Projects Execution | S52: 5 | T52: 5 | U52: 5 | Y52: 95 | Z52: - | AA52: 100 | AB52: Medium | AC52: High | AD52: Yes | AE52: - | AH52: - | AI52: - | AJ52: - | AK52: - | AL52: -
A53: 24900041 | B53: Vijay Anandrao Pachupate | C53: Chief Manager - Quality | D53: Sterlite Electric | E53: M4A | F53: Shinde, Baban Ramchandra | G53: Piparia Plant - DNH | I53: 2.2 | J53: 29.5 | K53: Head- Strategy & M&A (2026-Present), VP - Strategy & Finance, MD Office (2024-2026) | L53: Suminter India Organic (2023-2024), Bajaj Electricals Ltd (2019-2023), Voltas Ltd (2016-2019) | M53: QHSE | S53: 5 | T53: 5 | U53: 5 | Y53: 80 | Z53: 88 | AA53: 100 | AB53: Low | AC53: High | AD53: Yes | AE53: - | AH53: - | AI53: - | AJ53: - | AK53: - | AL53: -
A54: 35001914 | B54: Mukesh Sharma | C54: Chief Manager - Sales & Business Development | D54: Sterlite Electric | E54: M4 | F54: Malhotra, Nitin | G54: Project Site - GJ | I54: 1.8 | J54: 12 | K54: Chief Business Officer - Overhead & MSI (2021-Present) , Vice President Projects (2019-2021) | L54: Punj Lloyd Limited (2008-2019), Bharat Heavy Electricals Limited (2002-2007), Honda Motorcycle & Scooter India Pvt. Ltd. (2002 – 2002) | M54: Sales | S54: 5 | T54: - | U54: - | Y54: 105 | Z54: 102 | AA54: 110 | AB54: Medium | AC54: Medium | AD54: No | AE54: - | AH54: - | AI54: - | AJ54: - | AK54: - | AL54: -
A55: 24902658 | B55: Chandan Sharma | C55: Assistant Vice President - Supply Chain, Logistics | D55: Sterlite Electric | E55: M3 | F55: Mattoo, Surinder | G55: Haridwar Plant - UKH | I55: 3.8 | J55: 14 | K55: CFO- SEL (2026- Present) | L55: Tenneco Clean Air India Limited (2024-2026), Azure Power India Pvt Ltd (2023-2024), Sterlite Power Transmission Ltd ( 2019-20223) | M55: Supply Chain Management | S55: 5 | T55: 5 | U55: 5 | Y55: 120 | Z55: 110 | AA55: 100 | AB55: Medium | AC55: High | AD55: Yes | AE55: - | AH55: - | AI55: - | AJ55: - | AK55: - | AL55: -
A56: 24900167 | B56: Bishwajit Banerjee | C56: Chief Manager - Production Planning & Control | D56: Sterlite Electric | E56: M4A | F56: Chowdhury, Ratul | G56: Rakholi Plant - DNH | I56: 7 | J56: 23.2 | K56: Head - Manufacturing Operations (2026-Present), Vice President - Manufacturing Operations (2024-2026) | L56: Indoasian Legrand Group (1999-2024) | M56: Manufacturing | S56: 5 | T56: 5 | U56: 4 | Y56: 80 | Z56: 88 | AA56: 100 | AB56: Medium | AC56: Medium | AD56: No | AE56: - | AH56: 78 | AI56: 79 | AJ56: 80 | AK56: - | AL56: -
A57: 24902352 | B57: Ramesh Sitaram Bidwai | C57: Chief Manager - Sales & Business Development (Overhead Products) | D57: Sterlite Electric | E57: M4A | F57: Chaturvedi, Siddharth | G57: Mumbai - Vikhroli | I57: 0 | J57: 19.7 | K57: Head- Strategy & M&A (2026-Present), VP - Strategy & Finance, MD Office (2024-2026) | L57: Suminter India Organic (2023-2024), Bajaj Electricals Ltd (2019-2023), Voltas Ltd (2016-2019) | M57: Sales | S57: 6 | T57: 5 | U57: 5 | Y57: 105 | Z57: 102 | AA57: 110 | AB57: High | AC57: High | AD57: Yes | AE57: - | AH57: 89 | AI57: 90 | AJ57: 88 | AK57: - | AL57: -
A58: 35000055 | B58: P Santhosh Kumar | C58: Chief Manager - Civil (PSS & TL) | D58: Serentica | E58: M4A | F58: Singh, Devanand | G58: Project Site - AP | I58: 2.2 | J58: 29.5 | K58: Chief Business Officer - Overhead & MSI (2021-Present) , Vice President Projects (2019-2021) | L58: Punj Lloyd Limited (2008-2019), Bharat Heavy Electricals Limited (2002-2007), Honda Motorcycle & Scooter India Pvt. Ltd. (2002 – 2002) | M58: Projects Execution | S58: 5 | T58: 5 | U58: 5 | Y58: 120 | Z58: 110 | AA58: 100 | AB58: Medium | AC58: Medium | AD58: Yes | AE58: - | AH58: 82 | AI58: 90 | AJ58: 89 | AK58: - | AL58: -
A59: 35001707 | B59: Giriraj Bohra | C59: Chief Manager- Projects (Solar) | D59: Serentica | E59: M4A | F59: Kumar, Mukesh | G59: Project Site - RJ | I59: 1.8 | J59: 12 | K59: CFO- SEL (2026- Present) | L59: Tenneco Clean Air India Limited (2024-2026), Azure Power India Pvt Ltd (2023-2024), Sterlite Power Transmission Ltd ( 2019-20223) | M59: Projects Execution | S59: 5 | T59: - | U59: - | Y59: 90 | Z59: 95 | AA59: 99 | AB59: Medium | AC59: High | AD59: Yes | AE59: - | AH59: 78 | AI59: 67 | AJ59: 91 | AK59: - | AL59: -
A60: 24901302 | B60: Nilotpal Mallick | C60: Assistant Vice President- PMT | D60: Serentica | E60: M3 | F60: Rathor, Satish | G60: Gurugram Office | I60: 3.8 | J60: 14 | K60: Head - Manufacturing Operations (2026-Present), Vice President - Manufacturing Operations (2024-2026) | L60: Indoasian Legrand Group (1999-2024) | M60: Projects Execution | S60: 5 | T60: 8 | U60: 5 | Y60: 95 | Z60: 98 | AA60: 100 | AB60: Low | AC60: High | AD60: Yes | AE60: - | AH60: 66 | AI60: 88 | AJ60: 82 | AK60: - | AL60: -
A61: 24903895 | B61: Mayank Bhatnagar | C61: Chief Manager - Business Development | D61: Serentica | E61: M4A | F61: DEWAN, SHILPY | G61: Gurugram Office | I61: 7 | J61: 23.2 | K61: Head- Strategy & M&A (2026-Present), VP - Strategy & Finance, MD Office (2024-2026) | L61: Suminter India Organic (2023-2024), Bajaj Electricals Ltd (2019-2023), Voltas Ltd (2016-2019) | M61: Business Acquisition | S61: 6 | T61: 5 | U61: 5 | Y61: 80 | Z61: 88 | AA61: 100 | AB61: Medium | AC61: Medium | AD61: No | AE61: - | AH61: 89 | AI61: 89 | AJ61: 90 | AK61: - | AL61: -
A62: 35001365 | B62: Manu Shukla | C62: Assistant Vice President - SCM (Wind) | D62: Serentica | E62: M3A | F62: Singh, Anil Kumar | G62: Gurugram Office | I62: 0 | J62: 19.7 | K62: Chief Business Officer - Overhead & MSI (2021-Present) , Vice President Projects (2019-2021) | L62: Punj Lloyd Limited (2008-2019), Bharat Heavy Electricals Limited (2002-2007), Honda Motorcycle & Scooter India Pvt. Ltd. (2002 – 2002) | M62: Supply Chain Management | S62: 8 | T62: 8 | U62: - | Y62: 105 | Z62: 102 | AA62: 110 | AB62: Low | AC62: Medium | AD62: Yes | AE62: - | AH62: - | AI62: - | AJ62: - | AK62: 96 | AL62: -
A63: 35001663 | B63: Annepureddy Kasi Eswara Reddy | C63: Chief Manager- Electrical (Wind) | D63: Serentica | E63: M4 | F63: RAJENDRAN, PREMKUMAR | G63: Project Site - KA | I63: 2.2 | J63: 29.5 | K63: CFO- SEL (2026- Present) | L63: Tenneco Clean Air India Limited (2024-2026), Azure Power India Pvt Ltd (2023-2024), Sterlite Power Transmission Ltd ( 2019-20223) | M63: Projects Execution | S63: 5 | T63: - | U63: - | Y63: 120 | Z63: 110 | AA63: 100 | AB63: Medium | AC63: Medium | AD63: Yes | AE63: - | AH63: 82 | AI63: 90 | AJ63: 89 | AK63: - | AL63: -
A64: 35001632 | B64: Srinivasa Rao Duvvuri | C64: Chief Manager Land Legal | D64: Serentica | E64: M4 | F64: Ananda, Thejala | G64: Project Site - AP | I64: 1.8 | J64: 12 | K64: Head - Manufacturing Operations (2026-Present), Vice President - Manufacturing Operations (2024-2026) | L64: Indoasian Legrand Group (1999-2024) | M64: Project Development | S64: 5 | T64: - | U64: - | Y64: 90 | Z64: 95 | AA64: 99 | AB64: Medium | AC64: Medium | AD64: Yes | AE64: - | AH64: 78 | AI64: 67 | AJ64: 91 | AK64: - | AL64: -
A65: 35000863 | B65: Rajendra Kumar Gupta | C65: Assistant Vice President - Projects (Solar) | D65: Serentica | E65: M3A | F65: Rathor, Satish | G65: Gurugram Office | I65: 3.8 | J65: 14 | K65: Head- Strategy & M&A (2026-Present), VP - Strategy & Finance, MD Office (2024-2026) | L65: Suminter India Organic (2023-2024), Bajaj Electricals Ltd (2019-2023), Voltas Ltd (2016-2019) | M65: Projects Execution | S65: 8 | T65: 6 | U65: 5 | Y65: 95 | Z65: 98 | AA65: 100 | AB65: Low | AC65: High | AD65: Yes | AE65: - | AH65: 66 | AI65: 88 | AJ65: 82 | AK65: 98 | AL65: 94
A66: 35001647 | B66: Pradeep Verma | C66: Assistant Vice President - Business Development | D66: Serentica | E66: M3 | F66: DEWAN, SHILPY | G66: Gurugram Office | I66: 7 | J66: 23.2 | K66: Chief Business Officer - Overhead & MSI (2021-Present) , Vice President Projects (2019-2021) | L66: Punj Lloyd Limited (2008-2019), Bharat Heavy Electricals Limited (2002-2007), Honda Motorcycle & Scooter India Pvt. Ltd. (2002 – 2002) | M66: Business Acquisition | S66: 5 | T66: - | U66: - | Y66: 80 | Z66: 88 | AA66: 100 | AB66: Medium | AC66: Medium | AD66: No | AE66: - | AH66: 89 | AI66: 89 | AJ66: 90 | AK66: - | AL66: -
A67: 35001765 | B67: Jaswant Singh | C67: Chief Manager- Legal | D67: Serentica | E67: M4 | F67: Chauhan, Pramod Singh | G67: Project Site - RJ | I67: 0 | J67: 19.7 | K67: CFO- SEL (2026- Present) | L67: Tenneco Clean Air India Limited (2024-2026), Azure Power India Pvt Ltd (2023-2024), Sterlite Power Transmission Ltd ( 2019-20223) | M67: Project Development | S67: 5 | T67: - | U67: - | Y67: 105 | Z67: 102 | AA67: 110 | AB67: Medium | AC67: Medium | AD67: No | AE67: - | AH67: - | AI67: - | AJ67: - | AK67: - | AL67: -
A68: 35001753 | B68: Selvaganapathi K | C68: Chief Manager- Design & Engineering | D68: Serentica | E68: M4 | F68: Kumar, Saravana | G68: Gurugram Office | I68: 2.2 | J68: 29.5 | K68: Head - Manufacturing Operations (2026-Present), Vice President - Manufacturing Operations (2024-2026) | L68: Indoasian Legrand Group (1999-2024) | M68: Design & Engineering | S68: 5 | T68: - | U68: - | Y68: 120 | Z68: - | AA68: - | AB68: Medium | AC68: Medium | AD68: Yes | AE68: - | AH68: - | AI68: - | AJ68: - | AK68: - | AL68: -
A69: 35001949 | B69: Jebas Chandra Bose T | C69: Chief Manager- Electrical (Wind- Annigeri) | D69: Serentica | E69: M4 | F69: Rakesh, Deepan | G69: Project Site - KA | I69: 1.8 | J69: 12 | K69: Head- Strategy & M&A (2026-Present), VP - Strategy & Finance, MD Office (2024-2026) | L69: Suminter India Organic (2023-2024), Bajaj Electricals Ltd (2019-2023), Voltas Ltd (2016-2019) | M69: Projects Execution | S69: 5 | T69: - | U69: - | Y69: - | Z69: - | AA69: - | AB69: Medium | AC69: Medium | AD69: Yes | AE69: - | AH69: - | AI69: - | AJ69: - | AK69: - | AL69: -
A70: 35002085 | B70: Ashwani Grover | C70: Chief Manager- Electrical Procurement | D70: Serentica | E70: M4 | F70: Sharma, Ashish | G70: Gurugram Office | I70: 3.8 | J70: 14 | K70: Chief Business Officer - Overhead & MSI (2021-Present) , Vice President Projects (2019-2021) | L70: Punj Lloyd Limited (2008-2019), Bharat Heavy Electricals Limited (2002-2007), Honda Motorcycle & Scooter India Pvt. Ltd. (2002 – 2002) | M70: Supply Chain Management | S70: 5 | T70: - | U70: - | Y70: 95 | Z70: - | AA70: 100 | AB70: Low | AC70: Medium | AD70: No | AE70: - | AH70: 78 | AI70: 79 | AJ70: 80 | AK70: - | AL70: -
A71: 35001904 | B71: Ashwary Sharma | C71: Chief Manager- Regulatory Affairs | D71: Serentica | E71: M4 | F71: Pierce, Tannhauser D | G71: Gurugram Office | I71: 7 | J71: 23.2 | K71: CFO- SEL (2026- Present) | L71: Tenneco Clean Air India Limited (2024-2026), Azure Power India Pvt Ltd (2023-2024), Sterlite Power Transmission Ltd ( 2019-20223) | M71: Policy and Regulatory | S71: 5 | T71: - | U71: - | Y71: 80 | Z71: 88 | AA71: 100 | AB71: Medium | AC71: Medium | AD71: No | AE71: - | AH71: 89 | AI71: 90 | AJ71: 88 | AK71: - | AL71: -
A72: 35001910 | B72: Sagar Sunil | C72: Chief Manager- Electrical (Wind) | D72: Serentica | E72: M4 | F72: Narayan, Surjeet | G72: Project Site - MH | I72: 0 | J72: 19.7 | K72: Head - Manufacturing Operations (2026-Present), Vice President - Manufacturing Operations (2024-2026) | L72: Indoasian Legrand Group (1999-2024) | M72: Projects Execution | S72: 5 | T72: - | U72: - | Y72: 105 | Z72: 102 | AA72: 110 | AB72: Medium | AC72: Low | AD72: Yes | AE72: - | AH72: 82 | AI72: 90 | AJ72: 89 | AK72: - | AL72: -
A73: 35001163 | B73: Yash Anil Goyal | C73: Chief Manager - Business Monitoring & Governance | D73: Serentica | E73: M4 | F73: Venkatramanan, Lakshmi Narayan | G73: Mumbai - BKC | I73: 2.2 | J73: 29.5 | K73: Head- Strategy & M&A (2026-Present), VP - Strategy & Finance, MD Office (2024-2026) | L73: Suminter India Organic (2023-2024), Bajaj Electricals Ltd (2019-2023), Voltas Ltd (2016-2019) | M73: Business Monitoring & Governance | S73: 6 | T73: - | U73: - | Y73: 120 | Z73: 110 | AA73: 100 | AB73: Medium | AC73: High | AD73: No | AE73: - | AH73: 78 | AI73: 67 | AJ73: 91 | AK73: - | AL73: -
A74: 35001141 | B74: Bigyan Parija | C74: Chief Operating Officer- Solar and Storage | D74: Serentica | E74: M1 | F74: Hiranandani, Akshay | G74: Gurugram Office | I74: 1.8 | J74: 12 | K74: Chief Business Officer - Overhead & MSI (2021-Present) , Vice President Projects (2019-2021) | L74: Punj Lloyd Limited (2008-2019), Bharat Heavy Electricals Limited (2002-2007), Honda Motorcycle & Scooter India Pvt. Ltd. (2002 – 2002) | M74: Projects Execution | S74: 8 | T74: 8 | U74: - | Y74: 80 | Z74: 88 | AA74: 100 | AB74: Medium | AC74: Medium | AD74: No | AE74: 4.2375 | AH74: 66 | AI74: 88 | AJ74: 82 | AK74: - | AL74: 73
A75: 35000795 | B75: Sandeep Chauhan | C75: Assistant Vice President - Land Acquisition | D75: Serentica | E75: M3A | F75: Dubey, Ravindra Kumar | G75: Gurugram Office | I75: 3.8 | J75: 14 | K75: CFO- SEL (2026- Present) | L75: Tenneco Clean Air India Limited (2024-2026), Azure Power India Pvt Ltd (2023-2024), Sterlite Power Transmission Ltd ( 2019-20223) | M75: Project Development | S75: 4 | T75: 4 | U75: 5 | Y75: 105 | Z75: - | AA75: - | AB75: High | AC75: Medium | AD75: No | AE75: - | AH75: 89 | AI75: 89 | AJ75: 90 | AK75: 98 | AL75: -
A76: 35001817 | B76: Basavaraj Kalyani Jevoor | C76: Chief Manager- Land Acquisition | D76: Serentica | E76: M4 | F76: Kale, Salil | G76: Project Site - KA | I76: 7 | J76: 23.2 | K76: Head - Manufacturing Operations (2026-Present), Vice President - Manufacturing Operations (2024-2026) | L76: Indoasian Legrand Group (1999-2024) | M76: Project Development | S76: 2 | T76: - | U76: - | Y76: 120 | Z76: 110 | AA76: 100 | AB76: High | AC76: Low | AD76: Yes | AE76: - | AH76: - | AI76: - | AJ76: - | AK76: - | AL76: -
A77: 35001611 | B77: Ganesh Paliwal | C77: Chief Manager- Projects (Solar) | D77: Serentica | E77: M4 | F77: Gupta, Rajendra Kumar | G77: Project Site - RJ | I77: 0 | J77: 19.7 | K77: Head- Strategy & M&A (2026-Present), VP - Strategy & Finance, MD Office (2024-2026) | L77: Suminter India Organic (2023-2024), Bajaj Electricals Ltd (2019-2023), Voltas Ltd (2016-2019) | M77: Projects Execution | S77: 5 | T77: - | U77: - | Y77: 90 | Z77: 95 | AA77: - | AB77: Medium | AC77: Medium | AD77: Yes | AE77: - | AH77: 82 | AI77: 90 | AJ77: 89 | AK77: - | AL77: -
A78: 35000687 | B78: Amit Ramnani | C78: Director - Risk and Finance | D78: Serentica | E78: M1 | F78: Hiranandani, Akshay | G78: Mumbai - BKC | I78: 2.2 | J78: 29.5 | K78: Chief Business Officer - Overhead & MSI (2021-Present) , Vice President Projects (2019-2021) | L78: Punj Lloyd Limited (2008-2019), Bharat Heavy Electricals Limited (2002-2007), Honda Motorcycle & Scooter India Pvt. Ltd. (2002 – 2002) | M78: Business Monitoring & Governance | S78: 8 | T78: 9 | U78: 8 | Y78: 95 | Z78: 98 | AA78: 100 | AB78: High | AC78: High | AD78: No | AE78: 3.8975 | AH78: 78 | AI78: 67 | AJ78: 91 | AK78: - | AL78: 90
A79: 35001708 | B79: Balamurugan MK | C79: Chief Manager- Wind Resource Assessment | D79: Serentica | E79: M4A | F79: Harsora, Arti | G79: Gurugram Office | I79: 1.8 | J79: 12 | K79: CFO- SEL (2026- Present) | L79: Tenneco Clean Air India Limited (2024-2026), Azure Power India Pvt Ltd (2023-2024), Sterlite Power Transmission Ltd ( 2019-20223) | M79: Projects Execution | S79: 5 | T79: - | U79: - | Y79: 80 | Z79: 88 | AA79: 100 | AB79: Medium | AC79: High | AD79: No | AE79: - | AH79: 66 | AI79: 88 | AJ79: 82 | AK79: - | AL79: -
A80: 35002080 | B80: Rajni Bansal | C80: Chief Manager- PMO (Land) | D80: Serentica | E80: M4 | F80: Nambiar, Amritesh Ramchandra | G80: Gurugram Office | I80: 3.8 | J80: 14 | K80: Head - Manufacturing Operations (2026-Present), Vice President - Manufacturing Operations (2024-2026) | L80: Indoasian Legrand Group (1999-2024) | M80: Projects Execution | S80: 5 | T80: - | U80: - | Y80: 105 | Z80: 102 | AA80: 110 | AB80: Low | AC80: Medium | AD80: Yes | AE80: - | AH80: 89 | AI80: 89 | AJ80: 90 | AK80: - | AL80: -
A81: 35001548 | B81: Tannhauser D Pierce | C81: Chief Manager- Policy | D81: Serentica | E81: M4A | F81: Kaistha, Kunal Lalit | G81: Gurugram Office | I81: 7 | J81: 23.2 | K81: Head- Strategy & M&A (2026-Present), VP - Strategy & Finance, MD Office (2024-2026) | L81: Suminter India Organic (2023-2024), Bajaj Electricals Ltd (2019-2023), Voltas Ltd (2016-2019) | M81: Policy and Regulatory | S81: 5 | T81: - | U81: - | Y81: 120 | Z81: 110 | AA81: 100 | AB81: Low | AC81: Medium | AD81: No | AE81: - | AH81: - | AI81: - | AJ81: - | AK81: - | AL81: -
A82: 35000854 | B82: Ashish Tukaram Kale | C82: Chief Manager - Land Acquisition | D82: Serentica | E82: M4A | F82: Patel, Prakash Veljibhai | G82: Project Site - MH | I82: 0 | J82: 19.7 | K82: Chief Business Officer - Overhead & MSI (2021-Present) , Vice President Projects (2019-2021) | L82: Punj Lloyd Limited (2008-2019), Bharat Heavy Electricals Limited (2002-2007), Honda Motorcycle & Scooter India Pvt. Ltd. (2002 – 2002) | M82: Project Development | S82: 6 | T82: 5 | U82: 5 | Y82: 90 | Z82: 95 | AA82: 99 | AB82: Low | AC82: High | AD82: Yes | AE82: - | AH82: - | AI82: - | AJ82: - | AK82: - | AL82: -
A83: 35001268 | B83: Mukesh Kumar | C83: Assistant Vice President- Projects (Solar) | D83: Serentica | E83: M3A | F83: Rathor, Satish | G83: Gurugram Office | I83: 2.2 | J83: 29.5 | K83: CFO- SEL (2026- Present) | L83: Tenneco Clean Air India Limited (2024-2026), Azure Power India Pvt Ltd (2023-2024), Sterlite Power Transmission Ltd ( 2019-20223) | M83: Projects Execution | S83: 6 | T83: 5 | U83: - | Y83: 95 | Z83: 98 | AA83: 100 | AB83: Low | AC83: High | AD83: Yes | AE83: - | AH83: - | AI83: - | AJ83: - | AK83: - | AL83: 84
A84: 35000693 | B84: Debendra Chhetry | C84: Chief Manager - Supply Chain, Procurement | D84: Sterlite Electric | E84: M4 | F84: Mattoo, Surinder | G84: Rakholi Plant - DNH | I84: 1.8 | J84: 12 | K84: Head - Manufacturing Operations (2026-Present), Vice President - Manufacturing Operations (2024-2026) | L84: Indoasian Legrand Group (1999-2024) | M84: Supply Chain Management | S84: 6 | T84: 8 | U84: - | Y84: 80 | Z84: 88 | AA84: 100 | AB84: Medium | AC84: High | AD84: Yes | AE84: - | AH84: 82 | AI84: 90 | AJ84: 89 | AK84: 96 | AL84: -
A85: 24901670 | B85: Neelam Kad | C85: Chief Manager - PMO | D85: Sterlite Electric | E85: M4 | F85: Samant, Sanket | G85: Gurugram Office | I85: 3.8 | J85: 14 | K85: Head- Strategy & M&A (2026-Present), VP - Strategy & Finance, MD Office (2024-2026) | L85: Suminter India Organic (2023-2024), Bajaj Electricals Ltd (2019-2023), Voltas Ltd (2016-2019) | M85: Projects Execution | S85: 5 | T85: 5 | U85: - | Y85: 105 | Z85: 102 | AA85: 110 | AB85: Low | AC85: High | AD85: Yes | AE85: - | AH85: 78 | AI85: 67 | AJ85: 91 | AK85: - | AL85: -
A86: 35000954 | B86: Shuklambor Chakraborty | C86: Chief Manager - Service Delivery & Management | D86: Sterlite Electric | E86: M4 | F86: Dangat, Nilesh | G86: Project Site - RJ | I86: 7 | J86: 23.2 | K86: Chief Business Officer - Overhead & MSI (2021-Present) , Vice President Projects (2019-2021) | L86: Punj Lloyd Limited (2008-2019), Bharat Heavy Electricals Limited (2002-2007), Honda Motorcycle & Scooter India Pvt. Ltd. (2002 – 2002) | M86: Convergence | S86: 6 | T86: 5 | U86: 5 | Y86: 120 | Z86: - | AA86: - | AB86: Low | AC86: High | AD86: Yes | AE86: - | AH86: 66 | AI86: 88 | AJ86: 82 | AK86: - | AL86: -
A87: 24903327 | B87: Bhupendra Sachdeva | C87: Chief Manager - Projects | D87: Sterlite Electric | E87: M4 | F87: Sharma, Satyendra Kumar | G87: Gurugram Office | I87: 0 | J87: 19.7 | K87: CFO- SEL (2026- Present) | L87: Tenneco Clean Air India Limited (2024-2026), Azure Power India Pvt Ltd (2023-2024), Sterlite Power Transmission Ltd ( 2019-20223) | M87: Projects Execution | S87: 8 | T87: 6 | U87: 5 | Y87: - | Z87: - | AA87: - | AB87: High | AC87: High | AD87: Yes | AE87: - | AH87: 89 | AI87: 89 | AJ87: 90 | AK87: - | AL87: -
A88: 24902731 | B88: Udit Narayan | C88: Assistant Vice President - Sales & Business Development ( Overhead Products) | D88: Sterlite Electric | E88: M4A | F88: Bhardwaj, Ankit | G88: Gurugram Office | I88: 2.2 | J88: 29.5 | K88: Head - Manufacturing Operations (2026-Present), Vice President - Manufacturing Operations (2024-2026) | L88: Indoasian Legrand Group (1999-2024) | M88: Sales | S88: 5 | T88: 5 | U88: 5 | Y88: 95 | Z88: - | AA88: 100 | AB88: Medium | AC88: High | AD88: No | AE88: - | AH88: - | AI88: - | AJ88: - | AK88: - | AL88: -
A89: 35002054 | B89: Himanshu Bhati | C89: Plant Director - Haridwar | D89: Sterlite Electric | E89: M3 | F89: Biswas, Dhritiman | G89: Haridwar Plant - UKH | I89: 1.8 | J89: 12 | K89: Head- Strategy & M&A (2026-Present), VP - Strategy & Finance, MD Office (2024-2026) | L89: Suminter India Organic (2023-2024), Bajaj Electricals Ltd (2019-2023), Voltas Ltd (2016-2019) | M89: Manufacturing | S89: 5 | T89: - | U89: - | Y89: 80 | Z89: 88 | AA89: 100 | AB89: Medium | AC89: Medium | AD89: Yes | AE89: - | AH89: 82 | AI89: 90 | AJ89: 89 | AK89: 91 | AL89: -
A90: 24900213 | B90: Jamil R Khan | C90: Chief Manager - QA | D90: Sterlite Electric | E90: M4A | F90: Shinde, Baban Ramchandra | G90: Rakholi Plant - DNH | I90: 3.8 | J90: 14 | K90: Chief Business Officer - Overhead & MSI (2021-Present) , Vice President Projects (2019-2021) | L90: Punj Lloyd Limited (2008-2019), Bharat Heavy Electricals Limited (2002-2007), Honda Motorcycle & Scooter India Pvt. Ltd. (2002 – 2002) | M90: QHSE | S90: 5 | T90: 5 | U90: 5 | Y90: 105 | Z90: 102 | AA90: 110 | AB90: Medium | AC90: High | AD90: Yes | AE90: - | AH90: 78 | AI90: 67 | AJ90: 91 | AK90: - | AL90: -
A91: 35001594 | B91: Monica Madan | C91: Chief Financial Officer | D91: Sterlite Electric | E91: M2A | F91: Trefois, Frederic | G91: Gurugram Office | I91: 7 | J91: 23.2 | K91: CFO- SEL (2026- Present) | L91: Tenneco Clean Air India Limited (2024-2026), Azure Power India Pvt Ltd (2023-2024), Sterlite Power Transmission Ltd ( 2019-20223) | M91: Finance | S91: 5 | T91: 5 | U91: - | Y91: 120 | Z91: 110 | AA91: 100 | AB91: Medium | AC91: Medium | AD91: No | AE91: 3.3175 | AH91: 66 | AI91: 88 | AJ91: 82 | AK91: - | AL91: 78
A92: 35000434 | B92: Chirag P Makwana | C92: Chief Manager - PMO and SCM | D92: Sterlite Electric | E92: M4A | F92: Deshraj, Surya Rajshekhar | G92: Gurugram Office | I92: 0 | J92: 19.7 | K92: Head - Manufacturing Operations (2026-Present), Vice President - Manufacturing Operations (2024-2026) | L92: Indoasian Legrand Group (1999-2024) | M92: Convergence | S92: 6 | T92: 5 | U92: 5 | Y92: 80 | Z92: 88 | AA92: 100 | AB92: High | AC92: High | AD92: Yes | AE92: - | AH92: 89 | AI92: 89 | AJ92: 90 | AK92: - | AL92: -
A93: 35001863 | B93: Nelluri Gani Kumar | C93: Chief Manager- Electrical (Wind) | D93: Serentica | E93: M4 | F93: Narayan, Surjeet | G93: Project Site - MH | I93: 2.2 | J93: 29.5 | K93: Head- Strategy & M&A (2026-Present), VP - Strategy & Finance, MD Office (2024-2026) | L93: Suminter India Organic (2023-2024), Bajaj Electricals Ltd (2019-2023), Voltas Ltd (2016-2019) | M93: Projects Execution | S93: 5 | T93: - | U93: - | Y93: 105 | Z93: 102 | AA93: 110 | AB93: Medium | AC93: Medium | AD93: Yes | AE93: - | AH93: - | AI93: - | AJ93: - | AK93: - | AL93: -
A94: 35001568 | B94: Rajnish Sahu | C94: Chief Manager- Projects (Solar) | D94: Serentica | E94: M4A | F94: Kumar, Mukesh | G94: Project Site - RJ | I94: 1.8 | J94: 12 | K94: Chief Business Officer - Overhead & MSI (2021-Present) , Vice President Projects (2019-2021) | L94: Punj Lloyd Limited (2008-2019), Bharat Heavy Electricals Limited (2002-2007), Honda Motorcycle & Scooter India Pvt. Ltd. (2002 – 2002) | M94: Projects Execution | S94: 5 | T94: - | U94: - | Y94: 120 | Z94: 110 | AA94: 100 | AB94: Low | AC94: High | AD94: Yes | AE94: - | AH94: - | AI94: - | AJ94: - | AK94: 99 | AL94: -
A95: 35001345 | B95: Mrigendra Rai | C95: Chief Manager- Contracts | D95: Serentica | E95: M4A | F95: Shukla, Manu | G95: Gurugram Office | I95: 3.8 | J95: 14 | K95: CFO- SEL (2026- Present) | L95: Tenneco Clean Air India Limited (2024-2026), Azure Power India Pvt Ltd (2023-2024), Sterlite Power Transmission Ltd ( 2019-20223) | M95: Supply Chain Management | S95: 5 | T95: 5 | U95: - | Y95: 90 | Z95: 95 | AA95: 99 | AB95: Medium | AC95: High | AD95: No | AE95: - | AH95: - | AI95: - | AJ95: - | AK95: - | AL95: -
A96: 35001730 | B96: Mahendrakumar Prakash Chaudhari | C96: Chief Manager- Design & Engineering | D96: Serentica | E96: M4A | F96: Kumar, Saravana | G96: Gurugram Office | I96: 7 | J96: 23.2 | K96: Head - Manufacturing Operations (2026-Present), Vice President - Manufacturing Operations (2024-2026) | L96: Indoasian Legrand Group (1999-2024) | M96: Design & Engineering | S96: 5 | T96: - | U96: - | Y96: 95 | Z96: 98 | AA96: 100 | AB96: High | AC96: Medium | AD96: Yes | AE96: - | AH96: - | AI96: - | AJ96: - | AK96: - | AL96: -
A97: 35001761 | B97: Gajendra Singh Mundel | C97: Assistant Vice President - Land Acquisition | D97: Serentica | E97: M3A | F97: Dubey, Ravindra Kumar | G97: Project Site - GJ | I97: 0 | J97: 19.7 | K97: Head- Strategy & M&A (2026-Present), VP - Strategy & Finance, MD Office (2024-2026) | L97: Suminter India Organic (2023-2024), Bajaj Electricals Ltd (2019-2023), Voltas Ltd (2016-2019) | M97: Project Development | S97: 5 | T97: 5 | U97: - | Y97: 80 | Z97: 88 | AA97: 100 | AB97: Medium | AC97: Medium | AD97: Yes | AE97: - | AH97: 78 | AI97: 79 | AJ97: 80 | AK97: 81 | AL97: -
A98: 35001842 | B98: Vaibhav Taneja | C98: Chief Manager- Commercial | D98: Serentica | E98: M4 | F98: Shukla, Manu | G98: Gurugram Office | I98: 2.2 | J98: 29.5 | K98: Chief Business Officer - Overhead & MSI (2021-Present) , Vice President Projects (2019-2021) | L98: Punj Lloyd Limited (2008-2019), Bharat Heavy Electricals Limited (2002-2007), Honda Motorcycle & Scooter India Pvt. Ltd. (2002 – 2002) | M98: Supply Chain Management | S98: 5 | T98: - | U98: - | Y98: 105 | Z98: 102 | AA98: 110 | AB98: Low | AC98: High | AD98: No | AE98: - | AH98: 89 | AI98: 90 | AJ98: 88 | AK98: - | AL98: -
A99: 35001784 | B99: Vikas Kushwaha | C99: Assistant Vice President- Project Development | D99: Serentica | E99: M3A | F99: J, Balakrishnan | G99: Gurugram Office | I99: 1.8 | J99: 12 | K99: CFO- SEL (2026- Present) | L99: Tenneco Clean Air India Limited (2024-2026), Azure Power India Pvt Ltd (2023-2024), Sterlite Power Transmission Ltd ( 2019-20223) | M99: Projects Execution | S99: 4 | T99: - | U99: - | Y99: 120 | Z99: 110 | AA99: 100 | AB99: Low | AC99: Low | AD99: No | AE99: - | AH99: 82 | AI99: 90 | AJ99: 89 | AK99: - | AL99: -
A100: 35001600 | B100: Sharad Vitthal Mane | C100: Chief Manager- Legal | D100: Serentica | E100: M4 | F100: Patel, Prakash Veljibhai | G100: Project Site - MH | I100: 3.8 | J100: 14 | K100: Head - Manufacturing Operations (2026-Present), Vice President - Manufacturing Operations (2024-2026) | L100: Indoasian Legrand Group (1999-2024) | M100: Project Development | S100: 5 | T100: - | U100: - | Y100: 90 | Z100: 95 | AA100: 99 | AB100: Low | AC100: High | AD100: No | AE100: - | AH100: 78 | AI100: 67 | AJ100: 91 | AK100: - | AL100: -
...

Sheet LOGO
A1: Company name | B1: Logo
A2: Resonia | B2: #VALUE!
A3: Serentica | B3: #VALUE!
A4: Sterlite | B4: #VALUE!
A5: Sterlite Electric | B5: #VALUE!

Sheet Future Readiness
A1: EmpID | B1: Timeline | C1: Role
A2: 35000971 | B2: Ready in 2-3 years | C2: Head - Indirect Tax (Group)
A3: 24902762 | B3: Ready now | C3: Chief Manager 1
A4: 35001624 | B4: Ready in 1-2 years | C4: Chief manager -M4 A
A5: 24903254 | B5: Ready in 2-3 years | C5: NPD
A6: 35001535 | B6: Ready in 1-2 years | C6: Head - Strategic Sourcing
A7: 24900980 | B7: Ready in 2-3 years | C7: Production Head
A8: 35001179 | B8: Ready now | C8: Head- Markets and Ops
A9: 24903846 | B9: Ready now | C9: BD Head and DCI Business India
A10: 35000592 | B10: Ready in 2-3 years | C10: Lead Regulatory
A11: 35000954 | B11: Ready now | C11: OPGW, HTLS, Conductors & Infra EPC Projects , Circle leaded
A12: 35000240 | B12: Ready now | C12: Circle Manager
A13: 35001689 | B13: Ready now | C13: HVDC PMT
... A157: 24901000 | B157: Ready now | C157: M&A and Equity Fund Raise

Sheet Competency Profile
A1: EmpID | B1: Type | C1: Item
A2: 24900040 | B2: Core Strength | C2: Good at SOP.
A3: 24900040 | B3: Development Area | C3: Need to further develop on Succession Planning.
A4: 24900041 | B4: Core Strength | C4: OPGW Quality Expert
A5: 24900041 | B5: Development Area | C5: Need to increase his knowledge in Conductor and take more ownership
A6: 24900062 | B6: Core Strength | C6: Adaptability Flexibility Collaboration Teamwork Accountability Integrity
A7: 24900062 | B7: Development Area | C7: 1) Commucnation 2) Substation techncial and costing
A8: 24900095 | B8: Core Strength | C8: Susmita is diligent and thorough about her work. She wears our values on her chest with pride.
A9: 24900095 | B9: Development Area | C9: 1. Communication - written and oral2. Delegation of work3. A bit of team management and grooming
A10: 24900122 | B10: Core Strength | C10: Strong connects and understanding on regulatory and regulatory authorities.
A11: 24900122 | B11: Development Area | C11: Needs to work on team management and bring system approach to regulatory.
A12: 24900167 | B12: Core Strength | C12: Good experience as a co-ordinator between Sales and Production, Sharing daily MIS updates on FG stock and sales nos.,Consolidation of Sales nos for overall OH business.
A13: 24900167 | B13: Development Area | C13: Need to expand roles possibly as overall Planner.
... A350: 35000745 | B350: Core Strength | C350: 1) Communication Clarity2) Leadership skills3) Goal Oriented Focus
A351: 35000745 | B351: Core Strength
A352: 35000745 | B352: Core Strength
A353: 35000745 | B353: Development Area | C353: 1) Process Improvement2) Regular Review Sessions
A354: 35000747 | B354: Core Strength | C354: Good relationship Management across the sector and informative market intelligence
A355: 35000747 | B355: Development Area | C355: May strengthen public relations with other stakeholders in the sector
A356: 35000749 | B356: Core Strength | C356: Extremely hard working, ability to be focused, patient on deliverables, and an excellent team member
A357: 35000749 | B357: Development Area | C357: To be more in the limelight and take initiative (has definitely improved from the last year)
A358: 35000795 | B358: Core Strength | C358: Land policies and land act knowledge is good.
A359: 35000795 | B359: Development Area | C359: He is handling important work portfolio but lacks initiatives and energy. Self motivation needs to be boosted.
A360: 35000803 | B360: Core Strength | C360: Highly motivated with the ability to take initiative Dedicated, disciplined, and committedGood communication skills with the ability to influence, negotiate
A361: 35000803 | B361: Development Area | C361: - Building deeper knowledge and hands-on experience in substation systems- Focus on developing stronger leadership presence through confident communication, strategic thinking, and polished professional interactions.
A362: 35000812 | B362: Core Strength | C362: Good Knowledge
A363: 35000812 | B363: Development Area | C363: Team Development , leadership skills
A364: 35000838 | B364: Core Strength | C364: Delivering on tough/non-glamorous/boring yet high-impact assignments; People management; Stakeholder management
... A831: 35002397 | B831: Development Area | C831: Needs to build her business Acumen

Sheet Actionable
A1: EmpID | C1: Type | D1: Action | E1: Status | F1: Remark | I1: Action Taken | J1: Action Proposed
A2: 35001397 | B2: =VLOOKUP(A2,Profile!A:A,1,0) -> #N/A | C2: Action Taken | D2: Strategy & Business Planning- More focus on Con, MSI | E2: To be Initiated | F2: Prashant to check with Pratik
A3: 35001397 | B3: =VLOOKUP(A3,Profile!A:A,1,0) -> #N/A | C3: Action Taken | D3: Coaching/Mentoring- Mentorship through Rakesh to young leaders - include this aspect as part of high potential program | E3: To be Initiated | F3: Will be part of High Pot program
A4: 35002222 | B4: =VLOOKUP(A4,Profile!A:A,1,0) -> #N/A | C4: Action Taken | D4: Role Alignment- Needs alignment on his role | E4: To be Initiated | F4: Prashant to check with Rohit
A5: 35001397 | B5: =VLOOKUP(A5,Profile!A:A,1,0) -> #N/A | C5: Action Taken | D5: Strategic Project Exposure- Play a key role in IPO - lead marketing, go on road shows with Frederic and Manish - needs to be communicated to Rakesh | E5: In Progress
A6: 35001880 | B6: =VLOOKUP(A6,Profile!A:A,1,0) -> #N/A | C6: Action Taken | D6: Feedback- Seek feedback from Arun and Prashant Sinha on the role he played in the Sankalp transformation | E6: In Progress
A7: 35001397 | B7: =VLOOKUP(A7,Profile!A:A,1,0) -> #N/A | C7: Action Taken | D7: Feedback- Emotional regulation | E7: Closed | F7: Feedback session completed with Pratik
A8: 35001397 | B8: =VLOOKUP(A8,Profile!A:A,1,0) -> #N/A | C8: Action Taken | D8: Role Change- Could be moved to live roles in business, well thought of line role (Sale, mfg, CTO?, +1) Opportunities eg accessories etc could be good to explore. CXO role in SEL . More like Lunmiker kind of opportunities Ruhie/Pratik to discuss | E8: Closed | F8: Conversation Completed & announced by Fredrick - will move to SEL (role movement in progress)
A9: 35001397 | B9: =VLOOKUP(A9,Profile!A:A,1,0) -> #N/A | C9: Action Taken | D9: Career Development Conversation- Career discussion with Pratik | E9: Closed | F9: Discussion done with Pratik, Ruhie & Rakesh
A10: 35000742 | B10: =VLOOKUP(A10,Profile!A:A,1,0) -> #N/A | C10: Action Taken | D10: Role Change- AOD: Ability to influence, ability to influence (cannot just convey strategy), should have his own point of view Career conversation in January with Pratik. Explore roles - move to a line function by June Potential roles: Roles: 1. Project Assurance in Resonia, issue is with the last mile delivery, might work if Prashant Sinha, we could add more (would this be a step up for him?) 2. CCO HVDC - Program Manager 3. Claims & contracts? 4. Cost Excellence Serentica? Maybe No Find a role where he does not need high amount of influencing | E10: Closed | F10: Discussion Completed with Pratik & Ruhie concluded - (Continue in current role for now)
A11: 35001880 | B11: =VLOOKUP(A11,Profile!A:A,1,0) -> #N/A | C11: Action Taken | D11: Capability Building- Rohit & Rakesh to work on M&A frameworking (Peer learning) | E11: Closed | F11: Not going ahead
A12: 35001880 | B12: =VLOOKUP(A12,Profile!A:A,1,0) -> #N/A | C12: Action Taken | D12: Career Development Conversation- He builds Internal SME Team. Possible areas for him Manufacturing focused projects? Ease the 33 kV load (Akshay), reverse engineering projects in Serentica Program manager for HVDC Strategy? (A MT can be assigned to him)- discussion with Pratik | E12: Closed | F12: discussion with Pratik done
A13: 35001141 | B13: =VLOOKUP(A13,Profile!A:A,1,0) -> 35001141 | C13: Action Taken | D13: No Immediate Action- No action | E13: NA
A14: 35001312 | B14: =VLOOKUP(A14,Profile!A:A,1,0) -> 35001312 | C14: Action Taken | D14: Feedback- Nudge Buddy: Will need constant feedback on the people management front; He needs to develop an appreciation of people skilled in ppl mgmt. | E14: In Progress | F14: Coach to be identified
A15: 35001312 | B15: =VLOOKUP(A15,Profile!A:A,1,0) -> 35001312 | C15: Action Taken | D15: Feedback- Needs to be given some assurance that there is some scope for failure to reduce perf anxiety | E15: In Progress | F15: Coach to be identified
A16: 35000365 | B16: =VLOOKUP(A16,Profile!A:A,1,0) -> 35000365 | C16: Action Taken | D16: Coaching/Mentoring- Continue to be coached | E16: In Progress | F16: Continue coaching for next 6 months
A17: 35001293 | B17: =VLOOKUP(A17,Profile!A:A,1,0) -> 35001293 | C17: Action Taken | D17: Role Enhancement- To support in oscillations for Serentica | E17: To be Initiated
A18: 35001293 | B18: =VLOOKUP(A18,Profile!A:A,1,0) -> 35001293 | C18: Action Taken | D18: Coaching/Mentoring- Get Tushar to peer mentor him, to inform him how O&M impacts IRR | E18: To be Initiated
A19: 35001293 | B19: =VLOOKUP(A19,Profile!A:A,1,0) -> 35001293 | C19: Action Taken | D19: Talent To be Assessed- Start assessing him on technical ability, rather than commercial ability (speaks to brand promise) | E19: In Progress
A20: 24900122 | B20: =VLOOKUP(A20,Profile!A:A,1,0) -> 24900122 | C20: Action Taken | D20: Successor Identification- Successor to be groomed | E20: To be Initiated
A21: 35000376 | B21: =VLOOKUP(A21,Profile!A:A,1,0) -> 35000376 | C21: Action Taken | D21: Capability Building- Place him in a course where he can network - wit IAS.IPS (MDI, Adm staff college Hyderabad)
A22: 35000376 | B22: =VLOOKUP(A22,Profile!A:A,1,0) -> 35000376 | C22: Action Taken | D22: Capability Building- Pratik can take him to events - All MH IAS/IPS
A23: 35001189 | B23: =VLOOKUP(A23,Profile!A:A,1,0) -> 35001189 | C23: Action Taken | D23: Capability Building- Put him in a COO program and groom him for next level | E23: To be Initiated
A24: 35001189 | B24: =VLOOKUP(A24,Profile!A:A,1,0) -> 35001189 | C24: Action Taken | D24: Capability Building- Stakeholder management to be enhanced | E24: In Progress | F24: Coach to be identified
A25: 24902503 | B25: =VLOOKUP(A25,Profile!A:A,1,0) -> 24902503 | C25: Action Taken | D25: Successor Identification- Identify and develop his successor , move him to PD | E25: To be Initiated
A26: 24902503 | B26: =VLOOKUP(A26,Profile!A:A,1,0) -> 24902503 | C26: Action Taken | D26: Capability Building- His stakeholder mgmt. skills needs to be enhanced | E26: In Progress | F26: Coach to be identified
A27: 24903214 | B27: =VLOOKUP(A27,Profile!A:A,1,0) -> 24903214 | C27: Action Taken | D27: Talent To be Assessed- Reassess after a while | E27: In Progress
A28: 35000686 | B28: =VLOOKUP(A28,Profile!A:A,1,0) -> 35000686 | C28: Action Taken | D28: Capability Building- Team management - seems demotivated | E28: In Progress
A29: 35000686 | B29: =VLOOKUP(A29,Profile!A:A,1,0) -> 35000686 | C29: Action Taken | D29: Capability Building- Connect in market | E29: In Progress
A30: 35000896 | B30: =VLOOKUP(A30,Profile!A:A,1,0) -> #N/A | C30: Action Taken | D30: Feedback- Delegation of work (Feedback through CEO track program) | E30: Closed | F30: Closed no action
A31: 35000896 | B31: =VLOOKUP(A31,Profile!A:A,1,0) -> #N/A | C31: Action Taken | D31: Capability Building- Need to develop a training program for his n-1 (Mattoo: Strategy; Dhritiman: Execution) | E31: Closed | F31: Closed no action
A32: 35000422 | B32: =VLOOKUP(A32,Profile!A:A,1,0) -> 35000422 | C32: Action Taken | D32: Successor Identification- Build the team under him | E32: Closed | F32: new role under consideration
A33: 35000422 | B33: =VLOOKUP(A33,Profile!A:A,1,0) -> 35000422 | C33: Action Taken | D33: Strategy & Business Planning- MD office to support Ankit B in business plan for the next year | E33: Closed | F33: new role under consideration
A34: 35000286 | B34: =VLOOKUP(A34,Profile!A:A,1,0) -> 35000286 | C34: Action Taken | D34: Strategy & Business Planning- Need for a strategic review of the Convergence business and firm up the plan on next steps ( target date September 2026). Need to create an opportunity to get investment, due to the push in data centre demands. We should focus on getting in some investments ideally by Sep 2026 (spin off) | E34: Closed | F34: closed - discussion with CEO initiated
A35: 35000286 | B35: =VLOOKUP(A35,Profile!A:A,1,0) -> 35000286 | C35: Action Taken | D35: Revision in Box Rating- Relook at Box rating - should be Box 6, bump up performance | E35: To be Initiated | F35: will be taken up in TR calibration for FY26
A36: 35000286 | B36: =VLOOKUP(A36,Profile!A:A,1,0) -> 35000286 | C36: Action Taken | D36: Capability Building- Identify a course for Strategy week long (with premiere institutes) | E36: To be Initiated | F36: to be identified by OTD
A37: 35000286 | B37: =VLOOKUP(A37,Profile!A:A,1,0) -> 35000286 | C37: Action Taken | D37: Capability Building- Identify a course on corporate finance (Raising equity, valution models - market caps etc., | E37: To be Initiated | F37: Post the above program to be identified
A38: 35001594 | B38: =VLOOKUP(A38,Profile!A:A,1,0) -> 35001594 | C38: Action Taken | D38: Org/team structure- Addition of resources in the team to manage work life balance due to exits | E38: Hold | F38: hold -positions on hold, appropriate call to be taken
A39: 35001594 | B39: =VLOOKUP(A39,Profile!A:A,1,0) -> 35001594 | C39: Action Taken | D39: Coaching/Mentoring- Mentoring from Sumil | E39: Closed | F39: closed
A40: 35001918 | B40: =VLOOKUP(A40,Profile!A:A,1,0) -> #N/A | C40: Action Taken | D40: Coaching/Mentoring- Coaching from Federic would help | E40: Closed | F40: closed
A41: 35001918 | B41: =VLOOKUP(A41,Profile!A:A,1,0) -> #N/A | C41: Action Taken | D41: Others- Goals to be shared with Pratik | E41: Closed | F41: done
... A89: 24901973 | B89: =VLOOKUP(A89,Profile!A:A,1,0) -> 24901973 | C89: Action Taken | D89: Feedback- Give feedback regarding discipline | E89: Closed | F89: AK, Ruhie has already gave him a feedback
A90: 35000877 | B90: =VLOOKUP(A90,Profile!A:A,1,0) -> 35000877 | C90: Action Taken | D90: Successor Identification- Check internal talent Akshay to meet Gauri & Aryaman | F90: to be dicsussed with Adnan
A91: 35000877 | B91: =VLOOKUP(A91,Profile!A:A,1,0) -> 35000877 | C91: Action Taken | D91: Replacement- Search for new legal head (external) | F91: to be dicsussed with Adnan
A92: 35000745 | B92: =VLOOKUP(A92,Profile!A:A,1,0) -> 35000745 | C92: Action Proposed | D92: Role Enhancement- Strategic Alignment, Moving beyond scope and budget to align project objectives with long-term business goals. | E92: Planned
A93: 35000172 | B93: =VLOOKUP(A93,Profile!A:A,1,0) -> 35000172 | C93: Action Proposed | D93: No Immediate Action | E93: Planned
A94: 35000985 | B94: =VLOOKUP(A94,Profile!A:A,1,0) -> 35000985 | C94: Action Proposed | D94: Role Change- Already role has been changed from Site in-charge to Electrical lead at Annigiri site, as per company requirement | E94: Planned
A95: 35001312 | B95: =VLOOKUP(A95,Profile!A:A,1,0) -> 35001312 | C95: Action Proposed | D95: No Immediate Action | E95: Planned
A96: 35001546 | B96: =VLOOKUP(A96,Profile!A:A,1,0) -> 35001546 | C96: Action Proposed | D96: No Immediate Action | E96: Planned
A97: 24900238 | B97: =VLOOKUP(A97,Profile!A:A,1,0) -> 24900238 | C97: Action Proposed | D97: No Immediate Action | E97: Planned
A98: 35001906 | B98: =VLOOKUP(A98,Profile!A:A,1,0) -> 35001906 | C98: Action Proposed | D98: - | E98: Planned
A99: 35001762 | B99: =VLOOKUP(A99,Profile!A:A,1,0) -> 35001762 | C99: Action Proposed | D99: - | E99: Planned
A100: 24903846 | B100: =VLOOKUP(A100,Profile!A:A,1,0) -> 24903846 | C100: Action Proposed | D100: Role Enhancement- With the Convergence BU expansion he need to be prepared for the higher responsibity | E100: Planned
A101: 35001657 | B101: =VLOOKUP(A101,Profile!A:A,1,0) -> 35001657 | C101: Action Proposed | D101: Feedback discussion- To discuss face to face during feed forward of H1 FY 27 Goal setting as by this time he will complete 1 year in system | E101: Planned
A102: 24900651 | B102: =VLOOKUP(A102,Profile!A:A,1,0) -> 24900651 | C102: Action Proposed | D102: No Immediate Action | E102: Planned
A103: 24901511 | B103: =VLOOKUP(A103,Profile!A:A,1,0) -> 24901511 | C103: Action Proposed | D103: - | E103: Planned
... A505: 35000851 | B505: =VLOOKUP(A505,Profile!A:A,1,0) -> 35000851 | C505: Action Proposed | D505: No Immediate Action | E505: Planned

Sheet Potential Successors
A1: EmpID | B1: Successor Name | C1: Readiness
A2: 35001888 | B2: Anandhakrishnan K M | C2: Ready in 1 to 2 years
A3: 24901052 | B3: Viren Kumar Patel | C3: Ready Now
A4: 35001830 | B4: Atul Sharma | C4: Ready Now
A5: 35001526 | B5: Ratneswar Mukherjee | C5: Ready Now
A6: 35001467 | B6: Deependra Singh | C6: Ready Now
A7: 35001214 | B7: Anshul Tripathi | C7: Ready Now
A8: 35001146 | B8: Anmol Maheshwari | C8: Ready in 1 to 2 years
A9: 35001578 | B9: Anisha Chopra | C9: Ready Now
A10: 35001186 | B10: Alisha Singh | C10: Ready in 2 to 3 years
A11: 35001525 | B11: Smruti Sephali Gouda | C11: Ready in 2 to 3 years
A12: 35000426 | B12: Shantanu Bhardwaj | C12: Ready in 2 to 3 years
A13: 35001691 | B13: Nabyendu Mukherjee | C13: Ready in 1 to 2 years
... A160: 35000681 | B160: Shashi Bhadoola | C160: Ready in 2 to 3 years
A161: admin01 | B161: Urvashi Jindal | C161: Ready Now
A162: admin01 | B162: Urvashi Jindal | C162: Ready Now
A163: 35001132 | B163: Amit Kumar Singh | C163: Ready in 2 to 3 years
A164: 35001040 | B164: Akash Srivastava | C164: Ready in 1 to 2 years
A165: 35001040 | B165: Akash Srivastava | C165: Ready in 1 to 2 years
A166: 35001032 | B166: Shivani Srivastava | C166: Ready in 1 to 2 years
A167: 35001028 | B167: Somraj Kar | C167: Ready Now
A168: 35001028 | B168: Somraj Kar | C168: Ready Now
A169: 24902092 | B169: Deepak Rathore | C169: Ready in 3+ years
A170: 24902066 | B170: Ashok Kumar Chauhan | C170: Ready in 1 to 2 years
A171: 24902272 | B171: K Vijaya Kumar | C171: Ready Now
A172: 35000423 | B172: Abhishek Garg | C172: Ready in 2 to 3 years
A173: 35001405 | B173: Pragya Agrawal | C173: Ready in 2 to 3 years
A174: 35000636 | B174: Rohit Ishwarrao Muppidwar | C174: Ready in 1 to 2 years
... A203: 35000393 | B203: Rajesh Mathankar | C203: Ready in 2 to 3 years
